kv_database/__init__.py
keyvalue_database-0.1.2.dist-info/LICENSE.txt
keyvalue_database-0.1.2.dist-info/METADATA
keyvalue_database-0.1.2.dist-info/WHEEL
keyvalue_database-0.1.2.dist-info/top_level.txt
keyvalue_database-0.1.2.dist-info/RECORD
