Metadata-Version: 2.1
Name: keyvalue-database
Version: 0.1.2
Summary: Key Value DataBase
Home-page: https://github.com/AhmadZ1/Key-Value-DataBase
Author: Ahmad Zaaroura
Author-email: ahmad.zaaroura.123@gmail.com
License: MIT
Keywords: DataBase
Platform: UNKNOWN
Classifier: Programming Language :: Python :: 3
Classifier: License :: OSI Approved :: MIT License
Classifier: Operating System :: OS Independent
Requires-Python: >=3.6
